{
    "10649": "Netherlands Women's",
    "10656": "Netherlands Women's",
    "10645": "Netherlands Women's",
    "49835": "Spain Women's",
    "46639": "Spain Women's",
    "32694": "Spain Women's",
    "45295": "Spain Women's",
    "50151": "Spain Women's",
    "10647": "Netherlands Women's",
    "62962": "Netherlands Women's",
    "10666": "Netherlands Women's",
    "49889": "Netherlands Women's",
    "47541": "Netherlands Women's",
    "32339": "Netherlands Women's",
    "10165": "Netherlands Women's",
    "15284": "Spain Women's",
    "10650": "Spain Women's",
    "63788": "Netherlands Women's",
    "10161": "Netherlands Women's",
    "10654": "Spain Women's",
    "10151": "Netherlands Women's",
    "50146": "Spain Women's",
    "32333": "Spain Women's",
    "222682": "Spain Women's",
    "49831": "Spain Women's",
    "50150": "Spain Women's",
    "46459": "Netherlands Women's",
    "62951": "Netherlands Women's",
    "49836": "Spain Women's",
    "63783": "Netherlands Women's",
    "50152": "Netherlands Women's",
    "10143": "Spain Women's",
    "221888": "Spain Women's"
}