{
    "5234": "Morocco",
    "139016": "Morocco",
    "6785": "Morocco",
    "7459": "Morocco",
    "5219": "Morocco",
    "46258": "Morocco",
    "3625": "Morocco",
    "10481": "France",
    "5487": "France",
    "5477": "Morocco",
    "4445": "France",
    "15890": "Morocco",
    "5237": "Morocco",
    "5245": "Morocco",
    "11990": "Morocco",
    "6704": "Morocco",
    "11135": "Morocco",
    "5485": "France",
    "3009": "Morocco",
    "6301": "Morocco",
    "3099": "France",
    "3604": "Morocco",
    "23774": "Morocco",
    "31295": "Morocco",
    "2972": "France",
    "59493": "Morocco",
    "21736": "Morocco",
    "22097": "France",
    "149714": "France"
}